simplebot_wikiquote.py
simplebot_wikiquote-1.0.0.dist-info/LICENSE
simplebot_wikiquote-1.0.0.dist-info/METADATA
simplebot_wikiquote-1.0.0.dist-info/WHEEL
simplebot_wikiquote-1.0.0.dist-info/entry_points.txt
simplebot_wikiquote-1.0.0.dist-info/top_level.txt
simplebot_wikiquote-1.0.0.dist-info/RECORD
